setup.cfg
setup.py
PyPocketExplore.egg-info/PKG-INFO
PyPocketExplore.egg-info/SOURCES.txt
PyPocketExplore.egg-info/dependency_links.txt
PyPocketExplore.egg-info/entry_points.txt
PyPocketExplore.egg-info/requires.txt
PyPocketExplore.egg-info/top_level.txt
pypocketexplore/__init__.py
pypocketexplore/api.py
pypocketexplore/cli.py
pypocketexplore/config.py
pypocketexplore/exceptions.py
pypocketexplore/model.py
pypocketexplore/parser.py