Metadata-Version: 1.0
Name: PyPocketExplore
Version: 1.0.0
Summary: PyPocketExplore - Unofficial API to Pocket Explore data
Home-page: http://tselai.com/pypocketexplore-collecting-exploring-predicting-pocket-items-machine-learning
Author: Florents Tselai
Author-email: florents.tselai@gmail.com
License: The MIT License (MIT) Copyright © 2017 Florents Tselai.
Platform: UNKNOWN
